{
    "produkty" :
        {
            "pizze":
                    [
                        {
                            "nazwa": "MARGARITA",
                            "ceny": 
                            {
                                "mała": "18zł",
                                "średnia" : "25zł",
                                "duża" : "30zł"
                            },
                            "składniki": "sos pomidorowy, ser, oregano, pomidor " ,
                            "zdjęcie": "margarita.jpg"
                        },
                        {
                            "nazwa": "PEPPERONI",
                            "ceny": 
                            {
                                "mała": "20zł",
                                "średnia" : "27zł",
                                "duża" : "35zł"
                            },
                            "składniki": "sos pomidorowy, ser, oregano, pepperoni, papryka ",
                            "zdjęcie": "pepperoni.jpg"
                        },
                        {
                            "nazwa": "CHICKEN",
                            "ceny": 
                            {
                                "mała": "21zł",
                                "średnia" : "28zł",
                                "duża" : "37zł"
                            },
                            "składniki": "sos pomidorowy, ser, oregano, kurczak, ananas, kukurydza, cebula ",
                            "zdjęcie": "chicken.jpg" 
                        }  

                    ],
            "sałatki":
                    [
                        {
                            "nazwa": "GRECKA",
                            "ceny": 
                            {
                                "mała": "7zł",
                                "średnia" : "10zł",
                                "duża" : "15zł"
                            },
                            "składniki": "sałata lodowa, pomidor, ogórek, papryka, cebula, kurczak ",
                            "zdjęcie": "greekSalade.jpg"  
                        }  

                    ],

            "frytki":
                    [
                        {
                            "nazwa": "FRYTKI Z ZIEMNIAKÓW",
                            "ceny": 
                            {
                                "mała": "5zł",
                                "średnia" : "7zł",
                                "duża" : "10zł"
                            },
                            "składniki": "",
                            "zdjęcie": "chips.jpg"  
                        },  
                        {
                            "nazwa": "FRYTKI Z BATATÓW",
                            "ceny": 
                            {
                                "mała": "7zł",
                                "średnia" : "9zł",
                                "duża" : "12zł"
                            },
                            "składniki": "",
                            "zdjęcie": "sweetPotatosChips.jpg"  
                        }
                    ],

            "napoje":
            [
                {
                    "nazwa": "PEPSI",
                    "ceny": 
                    {
                        "mała": "3zł",
                        "średnia" : "5zł",
                        "duża" : "9zł"
                    },
                    "składniki": "",
                    "zdjęcie": "pepsi.jpg"  
                },  
                {
                    "nazwa": "COLA",
                    "ceny": 
                    {
                        "mała": "3zł",
                        "średnia" : "5zł",
                        "duża" : "9zł"
                    },
                    "składniki": "",
                    "zdjęcie": "cola.jpg"  
                }
            ]
        }
}